jinja2_indent/__init__.py
jinja2_indent/extension.py
jinja2_indent-0.3.0.dist-info/LICENSE
jinja2_indent-0.3.0.dist-info/METADATA
jinja2_indent-0.3.0.dist-info/WHEEL
jinja2_indent-0.3.0.dist-info/RECORD
