Metadata-Version: 2.1
Name: jinja2-indent
Version: 0.3.0
Summary: A Jinja2 extension for managing indentation in templates.
License: MIT
Author: Mihail Mishakin
Author-email: x896321475@gmail.com
Maintainer: Mihail Mishakin
Maintainer-email: x896321475@gmail.com
Requires-Python: >=3.9,<4.0
Classifier: Development Status :: 4 - Beta
Classifier: License :: OSI Approved :: MIT License
Classifier: Operating System :: OS Independent
Classifier: Programming Language :: Python
Classifier: Programming Language :: Python :: 3
Classifier: Programming Language :: Python :: 3.9
Classifier: Programming Language :: Python :: 3.10
Classifier: Programming Language :: Python :: 3.11
Classifier: Programming Language :: Python :: 3.12
Classifier: Programming Language :: Python :: 3.13
Classifier: Programming Language :: Python :: 3 :: Only
Requires-Dist: jinja2 (>=3.0.0,<4.0.0)
Requires-Dist: jinja2-simple-tags (>=0.6.1,<0.7.0)
Project-URL: repository, https://github.com/dldevinc/jinja2-indent
